setup.py
randomimg/__init__.py
randomimg.egg-info/PKG-INFO
randomimg.egg-info/SOURCES.txt
randomimg.egg-info/dependency_links.txt
randomimg.egg-info/requires.txt
randomimg.egg-info/top_level.txt