Metadata-Version: 1.0
Name: randomimg
Version: 0.0.1
Summary: Random image generator
Home-page: https://gtsforum.xyz
Author: Adam Jenca
Author-email: jenca.a@gjh.sk
License: UNKNOWN
Platform: UNKNOWN
